xfpip/__init__.py
xfpip/wp.py
xfpip-1.0.dist-info/LICENSE
xfpip-1.0.dist-info/METADATA
xfpip-1.0.dist-info/WHEEL
xfpip-1.0.dist-info/top_level.txt
xfpip-1.0.dist-info/RECORD
