Metadata-Version: 2.1
Name: xfpip
Version: 1.0
Summary: 一个用于学习制作开源pip的包
Home-page: https://github.com/LunFengChen/xfpip
Author: LunFengChen
Author-email: 1622246366@qq.com
Classifier: Programming Language :: Python :: 3
Classifier: License :: OSI Approved :: MIT License
Classifier: Operating System :: OS Independent
Requires-Python: >=3
License-File: LICENSE
Requires-Dist: pillow
